win_app_packager-1.5.0.data/purelib/win_app_packager/__init__.py
win_app_packager-1.5.0.data/purelib/win_app_packager/__main__.py
win_app_packager-1.5.0.data/purelib/win_app_packager/run_win_app.py
win_app_packager-1.5.0.data/purelib/win_app_packager/win_app_package_builder.py
win_app_packager-1.5.0.data/purelib/win_app_packager/win_app_package_exe_config.py
win_app_packager-1.5.0.data/purelib/win_app_packager/win_app_package_win_pe_info.py
win_app_packager-1.5.0.data/purelib/win_app_packager/win_known_paths.py
win_app_packager-1.5.0.data/purelib/win_app_packager/BootStrap/obj/bootstrap-cli.exe
win_app_packager-1.5.0.data/purelib/win_app_packager/BootStrap/obj/bootstrap-gui.exe
win_app_packager-1.5.0.dist-info/LICENSE
win_app_packager-1.5.0.dist-info/METADATA
win_app_packager-1.5.0.dist-info/WHEEL
win_app_packager-1.5.0.dist-info/top_level.txt
win_app_packager-1.5.0.dist-info/RECORD
