Metadata-Version: 2.1
Name: win-app-packager
Version: 1.5.0
Summary: Python Win App Packager
Home-page: https://github.com/barry-scott/PythonWinAppPackager
Author: Barry Scott
Author-email: barry@barrys-emacs.org
License: Apache 2.0
Keywords: development
Classifier: Development Status :: 5 - Production/Stable
Classifier: Intended Audience :: Developers
Classifier: Topic :: Software Development :: Build Tools
Classifier: License :: OSI Approved :: Apache Software License
Classifier: Environment :: Win32 (MS Windows)
Classifier: Operating System :: Microsoft :: Windows :: Windows 7
Classifier: Programming Language :: Python :: 3 :: Only
Classifier: Programming Language :: Python :: 3.6
Classifier: Programming Language :: Python :: 3.7
Classifier: Programming Language :: Python :: 3.8
Classifier: Programming Language :: Python :: 3.9
License-File: LICENSE
Requires-Dist: namedstruct (>=1.2.2)
Requires-Dist: colour-text
